MANIFEST.in
README.md
setup.py
om_simple_encoder/__init__.py
om_simple_encoder/encoder.py
om_simple_encoder/encoder_v2.py
om_simple_encoder/model.py
om_simple_encoder/text_image_dm.py
om_simple_encoder/text_image_dm_v2.py
om_simple_encoder/train.py
om_simple_encoder/wrapper.py
om_simple_encoder/wrapper_clip.py
om_simple_encoder/wrapper_swin.py
om_simple_encoder.egg-info/PKG-INFO
om_simple_encoder.egg-info/SOURCES.txt
om_simple_encoder.egg-info/dependency_links.txt
om_simple_encoder.egg-info/requires.txt
om_simple_encoder.egg-info/top_level.txt
om_simple_encoder/clip/__init__.py
om_simple_encoder/clip/bpe_simple_vocab_16e6.txt.gz
om_simple_encoder/clip/clip.py
om_simple_encoder/clip/model.py
om_simple_encoder/clip/simple_tokenizer.py
om_simple_encoder/configs/RN.yaml
om_simple_encoder/configs/ViT.yaml