Metadata-Version: 2.1
Name: om-simple-encoder
Version: 0.1.3
Summary: OM Simple Encoder
Home-page: https://www.soco.ai
Author: kyusonglee
License: UNKNOWN
Platform: UNKNOWN
Classifier: Programming Language :: Python :: 3
Classifier: License :: Free for non-commercial use
Classifier: Operating System :: OS Independent
